ledgereth/__init__.py
ledgereth/__main__.py
ledgereth/_meta.py
ledgereth/accounts.py
ledgereth/comms.py
ledgereth/constants.py
ledgereth/exceptions.py
ledgereth/messages.py
ledgereth/objects.py
ledgereth/py.typed
ledgereth/transactions.py
ledgereth/utils.py
ledgereth/web3.py
ledgereth-0.9.1.dist-info/LICENSE
ledgereth-0.9.1.dist-info/METADATA
ledgereth-0.9.1.dist-info/WHEEL
ledgereth-0.9.1.dist-info/top_level.txt
ledgereth-0.9.1.dist-info/RECORD
