Metadata-Version: 2.1
Name: ledgereth
Version: 0.9.1
Summary: Library to interface with ledger-app-eth on Ledger hardware wallets
Home-page: https://github.com/mikeshultz/ledger-eth-lib
Author: Mike Shultz
Author-email: mike@mikeshultz.com
License: UNKNOWN
Keywords: solidity ethereum development
Platform: UNKNOWN
Classifier: Development Status :: 3 - Alpha
Classifier: Intended Audience :: Developers
Classifier: Topic :: Software Development :: Libraries
Classifier: License :: OSI Approved :: GNU General Public License v3 or later (GPLv3+)
Classifier: Programming Language :: Python :: 3
Classifier: Programming Language :: Python :: 3.8
Classifier: Programming Language :: Python :: 3.9
Classifier: Programming Language :: Python :: 3.10
Classifier: Programming Language :: Python :: 3.11
Provides-Extra: dev
Provides-Extra: docs
License-File: LICENSE
